aslabs/dependencies/config/__init__.py
aslabs/dependencies/config/config.py
aslabs_dependencies_config-0.0.4.dist-info/WHEEL
aslabs_dependencies_config-0.0.4.dist-info/METADATA
aslabs_dependencies_config-0.0.4.dist-info/RECORD
